momovu/__init__.py
momovu/_version.py
momovu/main.py
momovu/py.typed
momovu/lib/__init__.py
momovu/lib/cli_i18n.py
momovu/lib/configuration_manager.py
momovu/lib/constants.py
momovu/lib/exceptions.py
momovu/lib/icon_theme.py
momovu/lib/logger.py
momovu/lib/shortcuts_dialog.py
momovu/lib/spine_calculator.py
momovu/lib/sizes/__init__.py
momovu/lib/sizes/book_interior_sizes.py
momovu/lib/sizes/dustjacket_spine_widths.py
momovu/locale/momovu-cli.pot
momovu/locale/ar/LC_MESSAGES/momovu-cli.mo
momovu/locale/ar/LC_MESSAGES/momovu-cli.po
momovu/locale/bn/LC_MESSAGES/momovu-cli.mo
momovu/locale/bn/LC_MESSAGES/momovu-cli.po
momovu/locale/de/LC_MESSAGES/momovu-cli.mo
momovu/locale/de/LC_MESSAGES/momovu-cli.po
momovu/locale/en/LC_MESSAGES/momovu-cli.mo
momovu/locale/en/LC_MESSAGES/momovu-cli.po
momovu/locale/es/LC_MESSAGES/momovu-cli.mo
momovu/locale/es/LC_MESSAGES/momovu-cli.po
momovu/locale/fr/LC_MESSAGES/momovu-cli.mo
momovu/locale/fr/LC_MESSAGES/momovu-cli.po
momovu/locale/hi/LC_MESSAGES/momovu-cli.mo
momovu/locale/hi/LC_MESSAGES/momovu-cli.po
momovu/locale/id/LC_MESSAGES/momovu-cli.mo
momovu/locale/id/LC_MESSAGES/momovu-cli.po
momovu/locale/it/LC_MESSAGES/momovu-cli.mo
momovu/locale/it/LC_MESSAGES/momovu-cli.po
momovu/locale/ja/LC_MESSAGES/momovu-cli.mo
momovu/locale/ja/LC_MESSAGES/momovu-cli.po
momovu/locale/ko/LC_MESSAGES/momovu-cli.mo
momovu/locale/ko/LC_MESSAGES/momovu-cli.po
momovu/locale/pl/LC_MESSAGES/momovu-cli.mo
momovu/locale/pl/LC_MESSAGES/momovu-cli.po
momovu/locale/pt/LC_MESSAGES/momovu-cli.mo
momovu/locale/pt/LC_MESSAGES/momovu-cli.po
momovu/locale/ru/LC_MESSAGES/momovu-cli.mo
momovu/locale/ru/LC_MESSAGES/momovu-cli.po
momovu/locale/tr/LC_MESSAGES/momovu-cli.mo
momovu/locale/tr/LC_MESSAGES/momovu-cli.po
momovu/locale/zh/LC_MESSAGES/momovu-cli.mo
momovu/locale/zh/LC_MESSAGES/momovu-cli.po
momovu/models/__init__.py
momovu/models/base.py
momovu/models/configuration.py
momovu/models/document.py
momovu/models/margin_settings.py
momovu/models/search.py
momovu-1.6.6.dist-info/licenses/LICENSE-apache.txt
momovu-1.6.6.dist-info/METADATA
momovu-1.6.6.dist-info/WHEEL
momovu-1.6.6.dist-info/entry_points.txt
momovu-1.6.6.dist-info/top_level.txt
momovu-1.6.6.dist-info/RECORD
