Metadata-Version: 2.4
Name: momovu
Version: 1.6.6
Summary: Preview dustjackets, covers, and interior pages of print books before publication
Author-email: Jeff Moe <moe@spacecruft.org>
License: Apache 2.0
Project-URL: Homepage, https://momovu.org
Project-URL: Documentation, https://momovu.org
Project-URL: Repository, https://spacecruft.org/books/momovu
Project-URL: Issues, https://spacecruft.org/books/momovu/issues
Project-URL: Changelog, https://spacecruft.org/books/momovu/raw/branch/main/CHANGELOG.txt
Classifier: Development Status :: 5 - Production/Stable
Classifier: Environment :: X11 Applications :: Qt
Classifier: Intended Audience :: End Users/Desktop
Classifier: License :: OSI Approved :: Apache Software License
Classifier: Natural Language :: Arabic
Classifier: Natural Language :: Bengali
Classifier: Natural Language :: Chinese (Simplified)
Classifier: Natural Language :: English
Classifier: Natural Language :: French
Classifier: Natural Language :: German
Classifier: Natural Language :: Hindi
Classifier: Natural Language :: Indonesian
Classifier: Natural Language :: Italian
Classifier: Natural Language :: Japanese
Classifier: Natural Language :: Korean
Classifier: Natural Language :: Polish
Classifier: Natural Language :: Portuguese
Classifier: Natural Language :: Russian
Classifier: Natural Language :: Spanish
Classifier: Natural Language :: Turkish
Classifier: Operating System :: POSIX :: Linux
Classifier: Programming Language :: Python :: 3
Classifier: Topic :: Multimedia :: Graphics :: Viewers
Classifier: Topic :: Printing
Requires-Python: >=3.9
License-File: LICENSE-apache.txt
Requires-Dist: PySide6<7.0.0,>=6.2.0
Requires-Dist: PyMuPDF>=1.23.0
Provides-Extra: dev
Requires-Dist: bandit>=1.8.6; extra == "dev"
Requires-Dist: black>=23.0.0; extra == "dev"
Requires-Dist: build>=0.10.0; extra == "dev"
Requires-Dist: dead>=2.1.0; extra == "dev"
Requires-Dist: flake8>=6.0.0; extra == "dev"
Requires-Dist: flake8-pyproject>=1.2.0; extra == "dev"
Requires-Dist: hypothesis>=6.100.0; extra == "dev"
Requires-Dist: hypothesis[pytest]>=6.100.0; extra == "dev"
Requires-Dist: isort>=5.12.0; extra == "dev"
Requires-Dist: mypy>=1.0.0; extra == "dev"
Requires-Dist: pytest>=7.0.0; extra == "dev"
Requires-Dist: pytest-cov>=4.0.0; extra == "dev"
Requires-Dist: pytest-qt>=4.2.0; extra == "dev"
Requires-Dist: ruff>=0.1.0; extra == "dev"
Requires-Dist: setuptools-scm>=7.0.0; extra == "dev"
Requires-Dist: transpolibre[all]; extra == "dev"
Requires-Dist: twine>=4.0.0; extra == "dev"
Requires-Dist: types-setuptools; extra == "dev"
Requires-Dist: vulture>=2.14; extra == "dev"
Provides-Extra: test
Requires-Dist: hypothesis>=6.100.0; extra == "test"
Requires-Dist: hypothesis[pytest]>=6.100.0; extra == "test"
Requires-Dist: pytest>=7.0.0; extra == "test"
Requires-Dist: pytest-cov>=4.0.0; extra == "test"
Requires-Dist: pytest-qt>=4.2.0; extra == "test"
Provides-Extra: docs
Requires-Dist: polib; extra == "docs"
Requires-Dist: pycountry; extra == "docs"
Requires-Dist: pygments; extra == "docs"
Requires-Dist: sphinx; extra == "docs"
Requires-Dist: sphinx-autobuild; extra == "docs"
Requires-Dist: sphinx-autodoc-typehints; extra == "docs"
Requires-Dist: sphinx-intl; extra == "docs"
Requires-Dist: sphinx-notfound-page; extra == "docs"
Requires-Dist: sphinx-rtd-theme; extra == "docs"
Requires-Dist: sphinxcontrib-markdown; extra == "docs"
Requires-Dist: sphinxcontrib-video; extra == "docs"
Dynamic: license-file
